ttkbootstrap_icons_bs/__init__.py
ttkbootstrap_icons_bs/icon.py
ttkbootstrap_icons_bs/provider.py
ttkbootstrap_icons_bs/assets/__init__.py
ttkbootstrap_icons_bs/assets/bootstrap.ttf
ttkbootstrap_icons_bs/assets/glyphmap.json
ttkbootstrap_icons_bs-1.0.0.dist-info/METADATA
ttkbootstrap_icons_bs-1.0.0.dist-info/WHEEL
ttkbootstrap_icons_bs-1.0.0.dist-info/entry_points.txt
ttkbootstrap_icons_bs-1.0.0.dist-info/top_level.txt
ttkbootstrap_icons_bs-1.0.0.dist-info/RECORD
